zood/__init__.py
zood/config/_config.yml
zood/config/error.log
zood/config/img/caution.svg
zood/config/img/clipboard-check.svg
zood/config/img/clipboard.svg
zood/config/img/enter.png
zood/config/img/enter.svg
zood/config/img/important.svg
zood/config/img/moon.png
zood/config/img/note.svg
zood/config/img/question.svg
zood/config/img/search.svg
zood/config/img/sun.png
zood/config/img/tip.svg
zood/config/img/warning.svg
zood/config/index.css
zood/config/js/change_mode.js
zood/config/js/copy_code.js
zood/config/js/dir_tree_toggle.js
zood/config/js/global_js_configuration.js
zood/config/js/navigator.js
zood/config/js/next_front.js
zood/config/js/picture_preview.js
zood/config/js/picture_title.js
zood/config/template.html
zood/extensions/__init__.py
zood/extensions/poetry_update.py
zood/gen_doc.py
zood/main.py
zood/server.py
zood/util.py
zood/zood.py
zood-0.13.12.dist-info/METADATA
zood-0.13.12.dist-info/WHEEL
zood-0.13.12.dist-info/entry_points.txt
zood-0.13.12.dist-info/RECORD
