Metadata-Version: 2.3
Name: zood
Version: 0.13.12
Summary: web page documentation & comment generation documentation
License: MIT
Author: kamilu
Author-email: luzhixing12345@163.com
Requires-Python: >=3.8,<4.0
Classifier: License :: OSI Approved :: MIT License
Classifier: Programming Language :: Python :: 3
Classifier: Programming Language :: Python :: 3.8
Classifier: Programming Language :: Python :: 3.9
Classifier: Programming Language :: Python :: 3.10
Classifier: Programming Language :: Python :: 3.11
Classifier: Programming Language :: Python :: 3.12
Classifier: Programming Language :: Python :: 3.13
Requires-Dist: MarkdownParser (>=0.5.38,<0.6.0)
Requires-Dist: PyYAML (==6.0.2)
Requires-Dist: syntaxlight (>=0.1.55,<0.2.0)
Project-URL: Documentation, https://luzhixing12345.github.io/zood/
Project-URL: Repository, https://github.com/luzhixing12345/zood
